fivesim/__init__.py
fivesim/api.py
fivesim/enums.py
fivesim/errors.py
fivesim/fivesim.py
fivesim/json_response.py
fivesim/py.typed
fivesim/request.py
fivesim/response.py
fivesim-1.2.0.dist-info/LICENSE
fivesim-1.2.0.dist-info/METADATA
fivesim-1.2.0.dist-info/WHEEL
fivesim-1.2.0.dist-info/top_level.txt
fivesim-1.2.0.dist-info/RECORD
