Metadata-Version: 2.1
Name: fivesim
Version: 1.2.0
Summary: Python API client for 5sim.net
Author: Erik Pellizzon
Author-email: erikpellizzon@gmail.com
License: MIT License
Project-URL: documentation, https://docs.5sim.net
Project-URL: repository, https://github.com/ErikPelli/fivesim
Keywords: number,telephone-numbers,5sim,fivesim,python-5sim
Classifier: Development Status :: 5 - Production/Stable
Classifier: Intended Audience :: Developers
Classifier: License :: OSI Approved :: MIT License
Classifier: Topic :: Software Development :: Libraries
Classifier: Programming Language :: Python :: 3
Classifier: Typing :: Typed
Requires-Python: >=3.6
License-File: LICENSE
Requires-Dist: python-dateutil
Requires-Dist: requests
